MANIFEST.in
README
setup.py
tweeql/__init__.py
tweeql/aggregation.py
tweeql/builtin_functions.py
tweeql/exceptions.py
tweeql/field_descriptor.py
tweeql/function_registry.py
tweeql/operators.py
tweeql/query.py
tweeql/query_builder.py
tweeql/query_runner.py
tweeql/settings_loader.py
tweeql/status_handlers.py
tweeql/tuple_descriptor.py
tweeql/tweeql_parser.py
tweeql/twitter_fields.py
tweeql.egg-info/PKG-INFO
tweeql.egg-info/SOURCES.txt
tweeql.egg-info/dependency_links.txt
tweeql.egg-info/requires.txt
tweeql.egg-info/top_level.txt
tweeql.egg-info/zip-safe
tweeql/bin/tweeql-command-line.py
tweeql/extras/__init__.py
tweeql/extras/sentiment/__init__.py
tweeql/extras/sentiment/analysis.py
tweeql/extras/sentiment/package.py
tweeql/extras/sentiment/sentiment.pkl.gz
tweeql/extras/sentiment/test-nltk.py
tweeql/extras/sentiment/train-nltk.py