Metadata-Version: 1.0
Name: tweeql
Version: 0.2.1
Summary: A SQL-like query language for the Twitter API
Home-page: http://github.com/marcua/tweeql
Author: Adam Marcus
Author-email: tweeql@googlegroups.com
License: BSD
Keywords: twitter query sql library
Platform: UNKNOWN
